meu_wmctrl/__init__.py
meu_wmctrl/funcoes_teclado_mouse.py
meu_wmctrl/funcoes_wmctrl.py
meu_wmctrl-0.3.0.dist-info/METADATA
meu_wmctrl-0.3.0.dist-info/WHEEL
meu_wmctrl-0.3.0.dist-info/top_level.txt
meu_wmctrl-0.3.0.dist-info/RECORD
