Metadata-Version: 2.4
Name: meu_wmctrl
Version: 0.3.0
Summary: Um wrapper Python para automatizar tarefas com wmctrl e pynput.
Home-page: https://github.com/seu_usuario/projeto_meu_wmctrl
Author: Dado Beltrão
Author-email: Dado <dado@email.com>
Classifier: Programming Language :: Python :: 3
Classifier: License :: OSI Approved :: MIT License
Classifier: Operating System :: POSIX :: Linux
Classifier: Topic :: Desktop Environment
Requires-Python: >=3.8
Requires-Dist: pynput
